vampyhost.so
vamp/__init__.py
vamp/collect.py
vamp/frames.py
vamp/load.py
vamp/process.py
vamp-1.1.0.dist-info/DESCRIPTION.rst
vamp-1.1.0.dist-info/METADATA
vamp-1.1.0.dist-info/metadata.json
vamp-1.1.0.dist-info/RECORD
vamp-1.1.0.dist-info/top_level.txt
vamp-1.1.0.dist-info/WHEEL
