Metadata-Version: 2.0
Name: vamp
Version: 1.1.0
Summary: Use Vamp plugins for audio feature analysis.
Home-page: https://code.soundsoftware.ac.uk/projects/vampy-host
Author: Chris Cannam, George Fazekas
Author-email: cannam@all-day-breakfast.com
License: MIT
Platform: UNKNOWN
Classifier: Development Status :: 4 - Beta
Classifier: Intended Audience :: Science/Research
Classifier: Intended Audience :: Developers
Classifier: License :: OSI Approved :: MIT License
Classifier: Operating System :: MacOS :: MacOS X
Classifier: Operating System :: Microsoft :: Windows
Classifier: Operating System :: POSIX
Classifier: Programming Language :: Python
Classifier: Programming Language :: Python :: 2
Classifier: Programming Language :: Python :: 3
Classifier: Topic :: Multimedia :: Sound/Audio :: Analysis
Requires: numpy
